{
  "dateInfo": "৯ বৈশাখ ১৪৩৩ বঙ্গাব্দ, বৃহস্পতিবার, ইংরেজী: ২৩ এপ্রিল ২০২৬, ৫৪০ চৈতনাব্দ, কলি: ৫১২৭, সৌর: ১০ বৈশাখ, চান্দ্র: ৭ ত্রিবিক্রম মাস, ১৯৪৮ শকাব্দ /২০৮৩ বিক্রম সাম্বৎ, ২৫৬৯ বুদ্ধাব্দাঃ, বাংলাদেশ: ১০ বৈশাখ ১৪৩৩, ভারতীয় সিভিল: ৩ বৈশাখ ১৯৪৮, মৈতৈ: ৭ কালেন, আসাম: ৯ বহাগ, মুসলিম: ৬-জ্বিলকদ-১৪৪৭ হিজরী",
  "events": "শ্রীগঙ্গার আবির্ভাব",
  "sunInfo": "সূর্য উদয়: সকাল ০৫:৩২:৩৯ এবং অস্ত: বিকাল ০৬:২১:০০।",
  "moonInfo": "চন্দ্র উদয়: সকাল ১০:৪০:৩০(২৩) এবং অস্ত: রাত্রি ১২:৪৩:৩৮(২৩)।",
  "tithi": "শুক্ল পক্ষ |তিথি: সপ্তমী (ভদ্রা) সকাল ঘ ০২:২৫:৪১ দং ৫২/১৪/৩২.৫ পর্যন্ত",
  "nakshatra": "নক্ষত্র: পুনর্বসু সকাল ঘ ০২:২৪:৫৮ দং ৫২/১২/৪৫ পর্যন্ত পরে পুষ্যা",
  "karana": "করণ: গর বিকাল ঘ ০৩:৩০:৫২ দং ২৪/৫৫/৩২.৫ পর্যন্ত পরে বণিজ সকাল ঘ ০২:২৫:৪১ দং ৫২/১৪/৩২.৫ পর্যন্ত পরে বিষ্টি",
  "yoga": "যোগ: সুকর্মা সকাল ঘ ১১:৩৬:৫২ দং ১৫/১০/৩২.৫ পর্যন্ত পরে ধৃতি",
  "auspiciousTimes": "অমৃতযোগ: রাতি ০১:০৪:২৮ থেকে - ০৩:১৮:৫৮| মহেন্দ্রযোগ: দিন ০৫:৩২:৩৯ থেকে - ০৭:১৫:০৬ পর্যন্ত, তারপর ১০:৩৯:৫৯ থেকে - ০১:১৩:৪০ পর্যন্ত।",
  "inauspiciousTimes": "কুলিকবেলা: দিন ০৯:৪৮:৪৬ থেকে - ১০:৩৯:৫৯ পর্যন্ত।\nকুলিকরাতি: ০৯:২০:১৯ থেকে - ১০:০৫:০৯ পর্যন্ত। কালবেলা : দিন ০৩:০৮:৫৫ থেকে - ০৪:৪৪:৫৭ পর্যন্ত।\nবারবেলা: দিন ০৪:৪৪:৫৭ থেকে - ০৬:২১:০০ পর্যন্ত।",
  "lagna": "লগ্ন: মেষ রাশি সকাল ০৬:৪৩:১১ পর্যন্ত। বৃষ রাশি সকাল ০৮:৪১:০৬ পর্যন্ত। মিথুন রাশি সকাল ১০:৫৪:৪০ পর্যন্ত। কর্কট রাশি দুপুর ০১:১১:১০ পর্যন্ত। সিংহ রাশি দুপুর ০৩:২৩:৩৩ পর্যন্ত। কন্যা রাশি বিকাল ০৫:৩৪:৪৮ পর্যন্ত। তুলা রাশি বিকাল ০৭:৪৯:৫৫ পর্যন্ত। বৃশ্চিক রাশি রাত্র ১০:০৬:০৯ পর্যন্ত। ধনু রাশি রাত্রি ১২:১১:১১ পর্যন্ত। মকর রাশি শেষ রাত্রি ০১:৫৭:১৬ পর্যন্ত। কুম্ভ রাশি শেষ রাত্রি ০৩:২৯:৩৭ পর্যন্ত। মীন রাশি শেষ রাত্রি ০৪:৫৯:৩৭ পর্যন্ত।",
  "grahosphut": "রবি: ০/৯/২৪/১৭ (১) ৩ পদ\nচন্দ্র: ৩/৪/১৫/৪২ (৮) ১ পদ\nমঙ্গল: ১১/১৪/৯/২৫ (২৬) ৪ পদ\nবুধ: ১১/২২/৪২/৪৩ (২৭) ২ পদ\nবৃহস্পতি: ২/২৪/৯/৪৮ (৭) ২ পদ\nশুক্র: ১/৫/৩২/৪ (৩) ৩ পদ\nশনি: ১১/১১/৪৫/৪০ (২৬) ৩ পদ\nরাহু: ১০/১৪/১৫/২৮ (২৪) ৩ পদ\nকেতু: ৪/১৪/১৫/২৮ (১১) ১ পদ"
}