{
  "title": "",
  "tableData": [
    [
      "সন্ধ্যা",
      "আরম্ভ কাল",
      "সমাপ্তি কাল"
    ],
    [
      "সূর্য",
      "উদয় ০৫:১৩:৫৮",
      "অস্ত ০৬:৩৯:০৫"
    ],
    [
      "অরুনোদয় কাল",
      "ভোর ০৩:০৬:৪৯",
      "সকাল ০৫:১৩:৫৮"
    ],
    [
      "ব্রহ্ম মুহূর্ত্ত",
      "ভোর ০৩:৪৯:১২",
      "ভোর ০৪:৩১:৩৫"
    ],
    [
      "প্রাত সন্ধ্যা",
      "ভোর ০৪:১০:২৪",
      "সকাল ০৫:১৩:৫৮"
    ],
    [
      "প্রাত কাল",
      "সকাল ০৫:১৩:৫৮",
      "সকাল ০৭:৫৪:৫৯"
    ],
    [
      "সঙ্গব কাল",
      "সকাল ০৭:৫৪:৫৯",
      "সকাল ১০:৩৬:০১"
    ],
    [
      "মধ্যাহ্ন সন্ধ্যা",
      "সকাল ১০:৩৬:০১",
      "সকাল ১১:৫৬:৩১"
    ],
    [
      "মধ্যাহ্ন কাল",
      "সকাল ১০:৩৬:০১",
      "দুপুর ০১:১৭:০২"
    ],
    [
      "অভিজিত মুহূর্ত্ত",
      "সকাল ১১:২৯:৪১",
      "দুপুর ১২:২৩:২২"
    ],
    [
      "অপরাহ্ন কাল",
      "দুপুর ০১:১৭:০২",
      "বিকাল ০৩:৫৮:০৩"
    ],
    [
      "বিজয় মুহূর্ত্ত",
      "দুপুর ০২:১০:৪৩",
      "বিকাল ০৩:০৪:২৩"
    ],
    [
      "সায়াহ্ন কাল",
      "বিকাল ০৩:৫৮:০৩",
      "সন্ধ্যা ০৬:৩৯:০৫"
    ],
    [
      "গোধুলী",
      "বিকাল ০৬:২৫:৪০",
      "সন্ধ্যা ০৬:৪৯:৪০"
    ],
    [
      "সান্ধ্যকালীন/সায়ন সন্ধ্যা",
      "সন্ধ্যা ০৬:৩৯:০৫",
      "রাত্র ০৭:৪২:৩৪"
    ],
    [
      "নিশীত কাল",
      "রাত্র ১১:৩৫:২২",
      "রাত্র ১২:১৭:৪১"
    ]
  ],
  "meta": {
    "region": "bangladesh",
    "screen": "sandhya",
    "checkedOn": "2026-06-01",
    "contentHash": "6af0359b49de2d99e3a099ac33abdeec3678f2630d6f4137d9129cd5f333e4c6",
    "previousContentHash": "e2a4bb867b213733a1626df7390fd709b5de59240528aea07864d123bb0394d5",
    "previousCheckedOn": "2026-05-31",
    "contentLastChangedOn": "2026-06-01",
    "isUpdatedForToday": true,
    "isSameAsPreviousSnapshot": false,
    "isSameAsPreviousDay": false
  }
}