{
  "title": "",
  "tableData": [],
  "meta": {
    "region": "kolkata",
    "screen": "sandhya",
    "checkedOn": "2026-05-10",
    "contentHash": "ddf77b596a393949667175b79a77831d9f587869def0d8f843bee24f89509c09",
    "previousContentHash": "5f15255e752689fc7a273c522ad8d3c6fe55162c8eeeab19cdb668144795f9af",
    "previousCheckedOn": "2026-05-10",
    "contentLastChangedOn": "2026-05-10",
    "isUpdatedForToday": true,
    "isSameAsPreviousSnapshot": false,
    "isSameAsPreviousDay": false
  }
}