{
  "horoscopes": {
    "mesh": {
      "name": "মেষ (Aries)",
      "header": "মেষ রাশিফল (Friday, July 10, 2026)",
      "prediction": "অপ্রয়োজনীয় ব্যাপারে তর্ক করে সময় নষ্ট করবেন না। মনে রাখবেন তর্কে পাওয়ার কিছু নেই বরং কেবল হারাবার আছে।  আপনি কমিশন- ডিভিডেন্ট- বা রয়্যালটি থেকে বেনিফিট পাবেন।  মনে হচ্ছে সিনেমা-থিয়েটারে সন্ধ্যাযাপন বা আপনার স্ত্রীর সাথে সান্ধ্যভোজ আপনাকে এক আয়েসী এবং চমকপ্রদ মেজাজে রাখবে। আপনার ভালবাসার জীবনে আজ একটি সুন্দর মোড় আসবে। আপনি প্রেমে স্বর্গীয় অনুভূতি পেতে পারেন।  অফিসে আজ আপনাকে পরিস্থিতি বুঝে আচার ব্যবহার করা উচিত। যদি আপনার বলার দরকার না থাকে তো সেখানে আপনি চুপ থাকুন , কোনো কথা জবরদস্তি বলে আপনি নিজেকে সমস্যায় ফেলতে পারেন।  আজ সেরকমই একটি দিন যখন বিষয়গুলি আপনার ইচ্ছামাফিক চলে না। আপনার বিবাহিত জীবন আজকের আগে এত রঙিন ছিল না।",
      "luckyNumber": "শুভ সংখ্যা :- 6",
      "luckyColor": "শুভ  রং :- স্বচ্ছ এবং গোলাপী",
      "remedy": "প্রতিকার :- কোনো দরিদ্র ব্যক্তিকে সেদ্ধ করা শস্য দান করলে আপনি সুস্বাস্থ অর্জন করবেন।",
      "ratings": {
        "স্বাস্থ্য": 1,
        "ধন": 4,
        "পরিবার": 5,
        "ভালোবাসার বিষয়বস্তু": 4,
        "পেশা": 1,
        "বিবাহিত জীবন": 4
      }
    },
    "brishabh": {
      "name": "বৃষভ (Taurus)",
      "header": "বৃষভ রাশিফল (Friday, July 10, 2026)",
      "prediction": "অন্যদের সাথে খুশি ভাগ করে নেওয়ার মাধ্যমে স্বাস্হ্যের বিকাশ ঘটতে পারে। আজ, আপনি আপনার ব্যবসা জোরদার করতে কিছু গুরুত্বপূর্ণ সিদ্ধান্ত নিতে পারেন, যার জন্য আপনার নিকটবর্তী কেউ আর্থিকভাবে সহায়তা করতে পারে।  যদি পুরো পরিবার অন্তর্ভুক্ত থাকে তাহলে বিনোদন মজার হয়ে উঠবে। আপনার প্রেমিকার আবেগের চাহিদার সামনেও মাথা নোয়াবেন না। কর্মক্ষেত্রে যারা আপনার সাফল্য পথে বাধা ছিল তারা আপনার চোখের সামনে আজ একটি গুরুতর পতনের সম্মুখীন হবে। আজ আপনি ভালো ধারণায় পূর্ণ থাকবেন এবং আপনার পছন্দের ক্রিয়াকলাপ আপনাকে প্রত্যাশা বহির্ভূত লাভ এনে দেবে। আপনার স্ত্রীর আত্মীয়রা আজ আপনাদের বৈবাহিক সুখের ক্ষতির কারণ হতে পারেন।",
      "luckyNumber": "শুভ সংখ্যা :- 5",
      "luckyColor": "শুভ  রং :- সবুজ এবং ফিরোজা",
      "remedy": "প্রতিকার :- নিজেরদের মধ্যে প্রেম বৃদ্ধির জন্য দুজনে একসাথে বসে ভবন বিষ্ণুর মৎস্যভাতার কথা পাঠ করুন।",
      "ratings": {
        "স্বাস্থ্য": 5,
        "ধন": 4,
        "পরিবার": 4,
        "ভালোবাসার বিষয়বস্তু": 1,
        "পেশা": 3,
        "বিবাহিত জীবন": 1
      }
    },
    "mithun": {
      "name": "মিথুন (Gemini)",
      "header": "মিথুন রাশিফল (Friday, July 10, 2026)",
      "prediction": "সৃজনশীল শখ আপনাকে চাপমুক্ত রাখবে। অর্থনৈতিক দিকটি শক্তিশালী হওয়ার সম্ভাবনা রয়েছে। যদি আপনি কোনও ব্যক্তিকে অর্থ ধার দিয়ে থাকেন তবে আপনি আজ সেই টাকা ফেরত পাবেন বলে আশা করা হচ্ছে।  জিভকে সংযত করতে হবে যাতে বয়স্ক গুরুজনেদের অভিমানে আঘাত না লাগে। বাজে কথায় সময় নষ্ট না করে চুপ থাকা শ্রেয়। মনে রাখবেন সংবেদনশীল কাজ দিয়েই আমরা জীবনের মূল্য দিই। তাদের বোঝান যে আপনি তাদের ব্যাপারে যত্নশীল। সারাটা দিন খুশী এবং আনন্দের সুন্দর বার্তায় ভরে থাকবে। আজ আপনি মধ্যমণি হয়ে উঠবেন- এবং সাফল্য ভালোভাবে আপনার নাগালের মধ্যে আসবে। আপনি নিজেকে সময় দিতে জানেন আর আজকে তো আপনার বেশকিছু খালি সময় পাওয়ার সম্ভবনা রয়েছে। খালি সময়ে আজকে আপনি কোনো খেলা খেলতে পারেন বা জিম যেতে পারেন।  আজ আপনি আপনার স্ত্রীর সঙ্গে আপনার জীবনের শ্রেষ্ঠ দিন কাটাবেন।",
      "luckyNumber": "শুভ সংখ্যা :- 3",
      "luckyColor": "শুভ  রং :- কেশর এবং হলুদ",
      "remedy": "প্রতিকার :- দাম্পত্য সুখ প্রাপ্তির জন্য খাবারে জাফরানের প্রয়োগ করুন।",
      "ratings": {
        "স্বাস্থ্য": 4,
        "ধন": 5,
        "পরিবার": 2,
        "ভালোবাসার বিষয়বস্তু": 5,
        "পেশা": 5,
        "বিবাহিত জীবন": 5
      }
    },
    "karkat": {
      "name": "কর্কট (Cancer)",
      "header": "কর্কট রাশিফল (Friday, July 10, 2026)",
      "prediction": "সুখী জীবনের স্বার্থে নিজের একগুঁয়েমি দূর করুন, এরফলে নিছক সময় নষ্ট হয়।  অর্থনৈতিকভাবে, আজ একটি মিশ্র দিন হতে চলেছে। আপনি আজ আর্থিক মুনাফা অর্জন করতে পারেন, আপনার শব্দটি সত্যই শক্তিশালী করে।  আত্মীয়দের কাছে ছোট সফর আপনার ক্লান্তিকর দৈনিক কাজের সূচীর থেকে আরাম এবং হালকা মূহুর্ত আনবে। আপনার প্রেমে জন্য মন হবে- এবং এর প্রচুর পরিমাণে সুযোগ আসবে।  আপনি আপনার কাজে একটি বড় সিদ্ধান্ত নিতে চলেছেন। সময়মত এবং দ্রুত পদক্ষেপ গ্রহণ আপনাকে অন্যদের থেকে এগিয়ে রাখবে। আপনি আপনার অধস্তনদের কিছু দরকারী পরামর্শ কান দিয়ে শুনতে পারেন।   সম্ভবতঃ কোন দূরের জায়গা থেকে সন্ধ্যার শেষভাগে সুখবর আসতে পারে। আপনি কি জানেন যে আপনার স্ত্রী সত্যিই আপনার জন্য দেবদূত। আমাদের বিশ্বাস করবেন না?  আজ পর্যবেক্ষণ করুন এবং অনুভব করুন।",
      "luckyNumber": "শুভ সংখ্যা :- 7",
      "luckyColor": "শুভ  রং :- ক্রিম এবং সাদা",
      "remedy": "প্রতিকার :- বিছানার পাশে সারা রাত তামার পাত্রে জল রাখুন এবং পরদিন সকালে কাছাকাছি গাছের শিকড়ে জল ঢেলে আসুন স্বাস্থ্য উত্তম থাকবে।",
      "ratings": {
        "স্বাস্থ্য": 1,
        "ধন": 3,
        "পরিবার": 5,
        "ভালোবাসার বিষয়বস্তু": 5,
        "পেশা": 4,
        "বিবাহিত জীবন": 5
      }
    },
    "singha": {
      "name": "সিংহ (Leo)",
      "header": "সিংহ রাশিফল (Friday, July 10, 2026)",
      "prediction": "আপনি আপনার শারীরিক সক্ষমতা বজায় রাখতে কিছু ক্রীড়া কার্যকলাপ উপভোগ করতে পারেন।  আজ জমি বা যে কোনও সম্পত্তিতে বিনিয়োগ আপনার জন্য মারাত্মক হতে পারে। যতটা সম্ভব এই জাতীয় সিদ্ধান্ত নেওয়া এড়িয়ে চলুন।  আপনার বাচ্চার কোন পুরস্কার গ্রহণের অনুষ্ঠানে আমন্ত্রণ পেয়ে আপনি খুশি হবেন। সে আপনার প্রত্যাশামাফিক ফল করে আপনার স্বপ্নকে বাস্তবায়িত করেছে। আপনার প্রেমিকা আজ আপনার কাছে কিছু দাবি করতে পারে তবে আপনি ইচ্ছাগুলি পূরণ করতে সক্ষম হবেন না। এটি আপনার প্রিয়জনকে বিচলিত করতে পারে।  সহকর্মী এবং ঊর্ধ্বতনরা তাদের পূর্ণ সহযোগিতার বিস্তার ঘটাবেন তাই অফিসের কাজে গতি লাভ করবে। টিভি,মোবাইল ব্যবহার করা ভুল না কিন্তূ দরকারের থেকে বেশি ব্যবহার করলে আপনার সময় খারাব হতে পারে।  আপনার জীবন সঙ্গী আজ আপনাকে অতিরিক্ত বিশেষ সময় দেবেন।",
      "luckyNumber": "শুভ সংখ্যা :- 5",
      "luckyColor": "শুভ  রং :- সবুজ এবং ফিরোজা",
      "remedy": "প্রতিকার :-  গণেশ চল্লিশা পাঠ করলে এবং এবং মন্ত্র উচ্চারণ করলে আর্থিক পরিস্থিতির উন্নতি হবে।",
      "ratings": {
        "স্বাস্থ্য": 5,
        "ধন": 1,
        "পরিবার": 5,
        "ভালোবাসার বিষয়বস্তু": 3,
        "পেশা": 5,
        "বিবাহিত জীবন": 3
      }
    },
    "kanya": {
      "name": "কন্যা (Virgo)",
      "header": "কন্যা রাশিফল (Friday, July 10, 2026)",
      "prediction": "যেহেতু আপনি ভয়রূপী এক ভয়ঙ্কর দৈত্যের সাথে লড়ছেন, কাজেই কিছু ইতিবাচক চিন্তার ছাঁচে নিজের ভাবনাকে গড়ে নিন অন্যথায় আপনি এই ঘোর দৈত্যের নিষ্ক্রিয় এবং নির্মম শিকারে পরিণত হবেন। আপনার খরচে অপ্রত্যাশিত উত্থান আপনার মানসিক শান্তিকে বিঘ্নিত করবে। আপনি আজ কিছু সমস্যার সম্মুখীন হবেন- কিন্তু বাস্তবসম্মত হন এবং যারা সাহায্যের হাত প্রসারিত করেছে তাদের ​​থেকে অলৌকিক কিছু আশা করবেন না।  স্বপ্ন,দুশ্চিন্তা ছাড়ুন এবং আপনার প্রেমের সঙ্গীর সঙ্গ উপভোগ করুন। আজ উচ্চ সম্পাদনা এবং উচ্চ প্রোফাইলের দিন। আজকে সময়ের সোন্দর্যের দিকে তাকিয়ে দেখা যাচ্ছে যে আপনি নিজের জন্য সময় বার করতে পারেন কিন্তু হটাৎই অফিসের কোনো কাজ চলে আসায় আপনি নিজেকে সময় দিতে সফল হবেন না।  আজ বিবাহ আপনার জীবনে তার শ্রেষ্ঠ জায়গায় পৌঁছাবে।",
      "luckyNumber": "শুভ সংখ্যা :- 3",
      "luckyColor": "শুভ  রং :- কেশর এবং হলুদ",
      "remedy": "প্রতিকার :- যোগ্য ব্যক্তিকে বা কোনো সংস্কৃতি পরিষদের ব্যক্তিকে বই বা অন্যান্য পড়াশোনা সম্পর্কিত জিনিস দান করুন, এর ফলে আপনার আর্থিক উন্নতি ঘটবে।",
      "ratings": {
        "স্বাস্থ্য": 2,
        "ধন": 1,
        "পরিবার": 1,
        "ভালোবাসার বিষয়বস্তু": 5,
        "পেশা": 5,
        "বিবাহিত জীবন": 5
      }
    },
    "tula": {
      "name": "তুলা (Libra)",
      "header": "তুলা রাশিফল (Friday, July 10, 2026)",
      "prediction": "আপনার কাঁধে অনেক কিছু নির্ভর করবে এবং সিদ্ধান্ত গ্রহণের ক্ষেত্রে আপনার জন্য মনের স্বচ্ছতা গুরুত্বপূর্ণ হবে। আপনার অর্থ কোথায় ব্যয় হচ্ছে সেদিকে আপনার নজর রাখা দরকার, অন্যথায় আপনি আগামী সময়ে সমস্যার মুখোমুখি হতে পারেন।  পরিবারের সদস্যরা অত্যন্ত দাবীদার হবে। ভালবাসার ছলনা সমস্ত দিন আপনাকে আবদ্ধ করে রাখবে। শুধুমাত্র সুখ অনুভব করুন।  সৃজনশীল চাকরি সম্পন্ন নেটিভরা আজ বিভিন্ন সমস্যার মুখোমুখি হতে পারেন। আপনি সৃজনশীল কাজের চেয়ে কোনও কাজের গুরুত্ব অনুধাবন করতে পারেন।  যদি আপনি আজ কেনাকাটা করতে যান তাহলে আপনি নিজের জন্য একটি সুন্দর পোষাক নির্বাচন করবেন।   আজ, আপনি আপনার জীবন সঙ্গী স্যাকরিন চেয়ে মিষ্টি বুঝতে পারবেন।",
      "luckyNumber": "শুভ সংখ্যা :- 6",
      "luckyColor": "শুভ  রং :- স্বচ্ছ এবং গোলাপী",
      "remedy": "প্রতিকার :- বাড়ির নিয়মিত ধূপকাঠি জ্বালালে তা আপনার পারিবারিক জীবনে ভালো প্রভাব দেবে।",
      "ratings": {
        "স্বাস্থ্য": 3,
        "ধন": 2,
        "পরিবার": 1,
        "ভালোবাসার বিষয়বস্তু": 4,
        "পেশা": 2,
        "বিবাহিত জীবন": 4
      }
    },
    "brishchik": {
      "name": "বৃশ্চিক (Scorpio)",
      "header": "বৃশ্চিক রাশিফল (Friday, July 10, 2026)",
      "prediction": "অতীতের ভুল সিদ্ধান্তগুলি আজ হতাশা এবং মানসিক অশান্তির দিকে নিয়ে যাবে- আপনি নিরুপায় এবং তার পরে কি করতে হবে তা নির্ধারণ করতে অসমর্থ হতে পারেন- অন্যদের থেকে সাহায্য চান। ব্যবসায়িক কৃতিত্বের জন্য যাঁরা আপনার কাছে আসে তাঁদেরকে শুধু উপেক্ষা করুন। আপনার অত্যধিক শক্তি এবং অসাধারণ উদ্যম আপনার অনুকূলে ফলাফল আনতে পারে এবং গার্হস্থ্য উত্তেজনা প্রশমিত করতে পারে।  আপনি আপনার ভালোবাসার মানুষটির সাথে সাক্ষাৎ করায় প্রেম আপনার মন আচ্ছন্ন করে রাখবে। একটি কঠিন পর্যায়ের পর, দিনটি কর্মক্ষেত্রে সুন্দর কিছু সঙ্গে আপনাকে অবাক করবে।  আপনার প্রেমিক আপনাকে প্রাপ্ত সময় দেয় না আজকে আপনি এই অভযোগটা তাকে খোলাখুলি জানাতে পারেন।  আপনার পিতামাতা আপনার স্ত্রীকে আশীর্বাদ করতে পারে যা আজ সত্যিই বিস্ময়কর কিছু হবে, এবং যা শেষ পর্যন্ত আপনার বিবাহিত জীবনকে উন্নত করবে।",
      "luckyNumber": "শুভ সংখ্যা :- 7",
      "luckyColor": "শুভ  রং :- ক্রিম এবং সাদা",
      "remedy": "প্রতিকার :- নিজের ইষ্টদেবতাকে লাল সিঁদুর দিয়ে পূজা স্বাস্থ্যের জন্য লাভদায়ক।",
      "ratings": {
        "স্বাস্থ্য": 1,
        "ধন": 1,
        "পরিবার": 5,
        "ভালোবাসার বিষয়বস্তু": 5,
        "পেশা": 3,
        "বিবাহিত জীবন": 5
      }
    },
    "dhanu": {
      "name": "ধনু (Sagittarius)",
      "header": "ধনু রাশিফল (Friday, July 10, 2026)",
      "prediction": "নিজেকে কিছু খেলাধূলায় নিয়োজিত করুন যেহেতু এটি হল চিরস্থায়ী যৌবনের গোপন কথা। আজ, আপনি কোনও সহায়তা বা সহায়তা ছাড়াই অর্থ উপার্জন করতে সক্ষম হবেন।  সম্পর্কগুলির সাথে সম্বন্ধ এবং বন্ধন পুনরুজ্জীবিত করার দিন। দিনটি আপনার চারপাশে গোলাপের সুবাস বয়ে আনবে। ভালবাসার উচ্ছ্বাস উপভোগ করুন।  আপনি বড় কিছুর অংশ হয়ে আপনার প্রশংসা এবং পুরষ্কার জয় করবেন। সামাজিক তথা ধর্মীয় অনুষ্ঠানের জন্য শ্রেষ্ঠ দিন। যদি আপনি এবং আপনার স্ত্রী এই দিনগুলিতে খুব সুখী বোধ না করেন তাহলে আপনি আজ পাগলের মত মজা করতে পারেন।",
      "luckyNumber": "শুভ সংখ্যা :- 4",
      "luckyColor": "শুভ  রং :- বাদামি এবং ধূসর",
      "remedy": "প্রতিকার :- সন্যাসী দের খাদ্য দান করলে তা আপনার স্বাস্থ্যের ওপর ভালো প্রভাব দেবে।",
      "ratings": {
        "স্বাস্থ্য": 3,
        "ধন": 5,
        "পরিবার": 5,
        "ভালোবাসার বিষয়বস্তু": 4,
        "পেশা": 4,
        "বিবাহিত জীবন": 4
      }
    },
    "makar": {
      "name": "মকর (Capricorn)",
      "header": "মকর রাশিফল (Friday, July 10, 2026)",
      "prediction": "কর্মব্যস্ত দিন হওয়া সত্ত্বেও স্বাস্হ্য সুন্দর থাকবে। আপনি যদি ছাত্র হন এবং বিদেশে পড়াশোনা করতে চান তবে ঘরে বসে আর্থিক সঙ্কট আপনাকে আজ বিরক্ত করতে পারে।  বন্ধু-ব্যবসায়িক সহযোগী এবং আত্মীয়দের সাথে কারবার করার সময় আপনার আগ্রহকে রক্ষা করুন-যেহেতু তাঁরা আপনার প্রয়োজনের প্রতি বিবেচক নাও হতে পারেন। আপনার ভালোবাসার মানুষটি অত্যন্ত চাহিদাপূর্ণ ব্যবহার করায় প্রেম আজ গৌণ হয়ে দাঁড়াবে মনে হচ্ছে। আজ আপনি আপনার কাজে একটি অগ্রগতি দেখতে পাবেন। যা আপনি সবচেয়ে বেশি করতে ভালোবাসেন সেই জিনিসের সঙ্গে আপনার মেলামেশা এবং অনুসরণ করার জন্য আজ আপনার কাছে অতিরিক্ত সময় আছে।  আপনার খারাপ মেজাজ আপনার জীবন সঙ্গীনীর কিছু বিশেষ চমকপ্রদ জিনিসের দ্বারা ঠিক হয়ে যাবে।",
      "luckyNumber": "শুভ সংখ্যা :- 4",
      "luckyColor": "শুভ  রং :- বাদামি এবং ধূসর",
      "remedy": "প্রতিকার :- সাংসারিক জীবন আনন্দপূর্ণ করতে মহিলাদের সম্মান করুন এবং তাঁদের কোন ভাবে আঘাত করবেন না।",
      "ratings": {
        "স্বাস্থ্য": 5,
        "ধন": 3,
        "পরিবার": 1,
        "ভালোবাসার বিষয়বস্তু": 2,
        "পেশা": 3,
        "বিবাহিত জীবন": 2
      }
    },
    "kumbha": {
      "name": "কুম্ভ (Aquarius)",
      "header": "কুম্ভ রাশিফল (Friday, July 10, 2026)",
      "prediction": "আপনার স্বাস্হ্য ভালো করার খাতিরে লম্বা পায়চারীতে বেরোন। আপনার ভবিষ্যতকে সমৃদ্ধ করতে অতীতে আপনি যে সমস্ত অর্থ বিনিয়োগ করেছিলেন তা আজ ফলস্বরূপ ফল পাবে।  বাচ্চারা আপনাকে বাড়ির কাজ সম্পূর্ণ করতে সাহায্য করে। কারো কারোর জন্য নতুন প্রেম আপনার উদ্দীপনাকে জাগিয়ে তুলবে এবং আপনাকে এক উচ্ছল মেজাজে রাখবে। আপনি একটি সমষ্টিগত লক্ষ্যের দিকে একটি দলকে একত্র করে এবং একসঙ্গে কাজ করানোর জন্য একটি শক্তিশালী অবস্থানে আছেন।  এই রাশির লোকেরা খুব কৌতূহলোদ্দীপক হয়.এরা কখনো লোকেদের মাঝখানে থেকে খুশি হয় তো কখনো একা থেকে যদিও একা থাকা এতটা সহজ নয় তবুও আজকে আপনি নিজের জন্য কিছু সময় বার করতে পারবেন।  আপনি এবং আপনার স্ত্রী আজ আপনার বিবাহিত জীবনের শ্রেষ্ঠ মেমোরি তৈরি করবেন।",
      "luckyNumber": "শুভ সংখ্যা :- 2",
      "luckyColor": "শুভ  রং :- রুপোলি এবং সাদা",
      "remedy": "প্রতিকার :- স্বাস্থ্যের উন্নতির জন্য আপনার পকেট এ বা ওয়ালেট এ কোনো হলুদ কাপড়ের টুকরো রাখুন। হলুদ কাপড়ের টুকরো মন ভালো করার কাজ করবে।",
      "ratings": {
        "স্বাস্থ্য": 3,
        "ধন": 5,
        "পরিবার": 5,
        "ভালোবাসার বিষয়বস্তু": 5,
        "পেশা": 4,
        "বিবাহিত জীবন": 5
      }
    },
    "meen": {
      "name": "মীন (Pisces)",
      "header": "মীন রাশিফল (Friday, July 10, 2026)",
      "prediction": "কিছু মানসিক চাপ থাকা সত্ত্বেও স্বাস্হ্য সুন্দর থাকবে। যারা নিজের ঘনিষ্ঠজন বা আত্মীয়দের সাথে তাদের ব্যবসা পরিচালনা করছেন তাদের আজ খুব সতর্ক থাকা দরকার, অন্যথায় আর্থিক ক্ষতি হতে পারে।  যাদের সাথে আপনি কদাচিৎ সাক্ষাৎ করেন তাদের সাথে য়োগাযোগের ভালো দিন। আজ, আপনার প্রেমিকা আপনার নিজের অনুভূতিগুলি প্রকাশ্যে আপনার সামনে জানাতে পারবেন না, যা আপনাকে বিরক্ত করতে পারে।  ব্যবসায়ীদের জন্য ভালো দিন কারণ তারা আকস্মিক অপ্রত্যাশিত মুনাফা বা অভাবনীয় লাভ দেখতে পেতে পারেন। আজ আপনি বিচক্ষণতা ব্যবহার করে ঘরের লোকেদের সাথে কথা বলবেন যদি আপনি তা না করেন তাহলে অযথা লড়ায়ে আপনার সময় নষ্ট হতে পারে।  খুব বেশী প্রত্যাশা আজ আপনার বিবাহিত জীবনে দুঃখ নিয়ে আসতে পারে।",
      "luckyNumber": "শুভ সংখ্যা :- 9",
      "luckyColor": "শুভ  রং :- লাল এবং মারুন",
      "remedy": "প্রতিকার :- নদীতে কালো ও সাদা তিলের বীজ নিক্ষেপ করলে প্রেমিক ও প্রেমিকাদের মধ্যে সম্পর্ক মজবুত হবে।",
      "ratings": {
        "স্বাস্থ্য": 4,
        "ধন": 3,
        "পরিবার": 5,
        "ভালোবাসার বিষয়বস্তু": 2,
        "পেশা": 5,
        "বিবাহিত জীবন": 2
      }
    }
  },
  "meta": {
    "region": "global",
    "screen": "rashifal",
    "checkedOn": "2026-07-10",
    "contentHash": "8c1025fb01f7445d6da40eb9efeea9b7227a622065ac0b8a3a1b36f3b77b53ea",
    "previousContentHash": "8c1025fb01f7445d6da40eb9efeea9b7227a622065ac0b8a3a1b36f3b77b53ea",
    "previousCheckedOn": "2026-07-10",
    "contentLastChangedOn": "2026-07-10",
    "isUpdatedForToday": true,
    "isSameAsPreviousSnapshot": true,
    "isSameAsPreviousDay": false
  }
}